netbox_inventory/__init__.py
netbox_inventory/analyzers.py
netbox_inventory/choices.py
netbox_inventory/constants.py
netbox_inventory/filtersets.py
netbox_inventory/managers.py
netbox_inventory/navigation.py
netbox_inventory/search.py
netbox_inventory/signals.py
netbox_inventory/tables.py
netbox_inventory/template_content.py
netbox_inventory/urls.py
netbox_inventory/utils.py
netbox_inventory/version.py
netbox_inventory/api/__init__.py
netbox_inventory/api/serializers.py
netbox_inventory/api/urls.py
netbox_inventory/api/views.py
netbox_inventory/api/serializers_/__init__.py
netbox_inventory/api/serializers_/assets.py
netbox_inventory/api/serializers_/audit.py
netbox_inventory/api/serializers_/deliveries.py
netbox_inventory/api/serializers_/nested.py
netbox_inventory/forms/__init__.py
netbox_inventory/forms/assign.py
netbox_inventory/forms/bulk_add.py
netbox_inventory/forms/bulk_edit.py
netbox_inventory/forms/bulk_import.py
netbox_inventory/forms/create.py
netbox_inventory/forms/filters.py
netbox_inventory/forms/models.py
netbox_inventory/forms/reassign.py
netbox_inventory/graphql/__init__.py
netbox_inventory/graphql/filters.py
netbox_inventory/graphql/schema.py
netbox_inventory/graphql/types.py
netbox_inventory/migrations/0001_initial_prod.py
netbox_inventory/migrations/0002_alter_asset_serial.py
netbox_inventory/migrations/0003_add_inventoryitemgroup.py
netbox_inventory/migrations/0004_inventoryitemgroup_tree.py
netbox_inventory/migrations/0005_delivery_asset_delivery.py
netbox_inventory/migrations/0006_purchase_status.py
netbox_inventory/migrations/0007_alter_asset_unique_together_and_more.py
netbox_inventory/migrations/0008_alter_asset_device_type_alter_asset_module_type.py
netbox_inventory/migrations/0009_add_rack.py
netbox_inventory/migrations/0010_asset_description_inventoryitemtype_description.py
netbox_inventory/migrations/0011_alter_supplier_options.py
netbox_inventory/migrations/0012_add_auditflow.py
netbox_inventory/migrations/0013_add_audittrail.py
netbox_inventory-2.5.0.dist-info/licenses/LICENSE
netbox_inventory-2.5.0.dist-info/METADATA
netbox_inventory-2.5.0.dist-info/WHEEL
netbox_inventory-2.5.0.dist-info/top_level.txt
netbox_inventory-2.5.0.dist-info/RECORD
