Metadata-Version: 2.4
Name: netbox-inventory
Version: 2.5.0
Summary: Inventory asset management in NetBox
Author-email: Matej Vadnjal <matej.vadnjal@arnes.si>
License-Expression: MIT
Project-URL: Homepage, https://github.com/ArnesSI/netbox-inventory/
Project-URL: Bug Tracker, https://github.com/ArnesSI/netbox-inventory/issues/
Keywords: netbox,netbox-plugin,inventory
Classifier: Programming Language :: Python :: 3
Classifier: Operating System :: OS Independent
Requires-Python: >=3.12
License-File: LICENSE
Dynamic: license-file
